cli/__init__.py
cli/run.py
rulet-0.1.dist-info/METADATA
rulet-0.1.dist-info/WHEEL
rulet-0.1.dist-info/entry_points.txt
rulet-0.1.dist-info/top_level.txt
rulet-0.1.dist-info/RECORD
