Metadata-Version: 2.1
Name: rulet
Version: 0.1
Summary: Russian Roulette game
Home-page: https://github.com/WinterCitizen/roulette
